webhook_broker.py
webhook_broker_python-0.0.1.dist-info/LICENSE
webhook_broker_python-0.0.1.dist-info/METADATA
webhook_broker_python-0.0.1.dist-info/WHEEL
webhook_broker_python-0.0.1.dist-info/top_level.txt
webhook_broker_python-0.0.1.dist-info/RECORD
