Metadata-Version: 2.1
Name: webhook-broker-python
Version: 0.0.1
Summary: Python Worker Library for Webhook Broker
Home-page: https://github.com/imran2140/webhook-broker-python
Author: Imran Alam
Author-email: imran2140@gmail.com
License: UNKNOWN
Project-URL: Bug Tracker, https://github.com/imran2140/webhook-broker-python/issues
Platform: UNKNOWN
Classifier: Programming Language :: Python :: 3
Classifier: License :: OSI Approved :: MIT License
Classifier: Operating System :: OS Independent
Requires-Python: >=3.8
Requires-Dist: httpx (>=0.16.1)
